{"dateText": "MAY, TUESDAY 20. 1890", "dateFormated": "1890-05-20", "cityOrState": "Davison County", "geographicalLocations": ["W.S. Con", "Mitchell"], "people": ["Mrs Dr. Prescott"], "fullText": "Davison County W.S. Con --\nMitchell - guest of Mrs Dr.\nPrescott --", "summaryText": "Susan B. Anthony was a guest of Mrs Dr. Prescott in Mitchell, Davison County, W.S. Con was also mentioned.", "digital_id": "mss11049.mss11049-003_00008_00223", "file_id": 84, "page": "https://tile.loc.gov/image-services/iiif/service:mss:mss11049:mss11049-003:00091/full/pct:12.5/0/default.jpg", "entry_id": 1}