{"dateText": "FEBRUARY THURSDAY 5 1874", "dateFormated": "1874-02-05", "cityOrState": "Norwalk Ct-.", "geographicalLocations": [""], "people": ["Ms Sara M. S. Huntington"], "fullText": "Norwalk Ct-. \nMs Sara M. S. Huntington", "summaryText": "Journal entry dated February 5, 1874, written in Norwalk Ct-. Mentions Ms Sara M. S. Huntington.", "digital_id": "mss11049.mss11049-002_00107_00307", "file_id": 33, "page": "https://tile.loc.gov/image-services/iiif/service:mss:mss11049:mss11049-002:00139/full/pct:12.5/0/default.jpg", "entry_id": 1}