{"dateText": "Wea. SUN. JUNE 16, 1901 Ther.", "dateFormated": "1901-06-16", "cityOrState": "Fort Scott", "geographicalLocations": [""], "people": ["Mary Luther", "Dr Sarah C. Halls", "Fannie"], "fullText": "At Fort Scott - hot & dry - No signs of rain Mary Luther & I took dinner at Dr Sarah C. Halls everything nice - all cooked by her daughter Fannie -", "summaryText": "Susan B. Anthony is in Fort Scott and has dinner at Dr Sarah C. Halls with Mary Luther.", "digital_id": "mss11049.mss11049-004_00906_01049", "file_id": 73, "page": "https://tile.loc.gov/image-services/iiif/service:mss:mss11049:mss11049-004:00978/full/pct:25/0/default.jpg", "entry_id": 1}