{"dateText": "Memoranda.", "dateFormated": "", "cityOrState": "", "geographicalLocations": ["Notting Hill Sq.", "West London- Eng-", "Springdale"], "people": ["Mrs Ernestine L. Rose", "Car A. Biggs", "Ann L. Ralz"], "fullText": "Mrs Ernestine L. Rose\nCar A. Biggs\n19 Notting Hill Sq.\nWest London- Eng-\nAnn L. Ralz Springdale [?]", "summaryText": "Mrs Ernestine L. Rose, Car A. Biggs, and Ann L. Ralz are mentioned in this entry along with geographical locations Notting Hill Sq., West London- Eng-, and Springdale.", "digital_id": "mss11049.mss11049-002_00308_00407", "file_id": 78, "page": "https://tile.loc.gov/image-services/iiif/service:mss:mss11049:mss11049-002:00385/full/pct:12.5/0/default.jpg", "entry_id": 1}