{"dateText": "FRIDAY 19", "dateFormated": "1878-07-19", "cityOrState": "Rochester", "geographicalLocations": [""], "people": [""], "fullText": "Celebration 30th Anniversary of\nthe Woman's Rights Movement -\nUnitarian Church Rochester -", "summaryText": "Susan B. Anthony attends a celebration for the 30th Anniversary of the Woman's Rights Movement in Rochester.", "digital_id": "mss11049.mss11049-002_00633_00763", "file_id": 65, "page": "https://tile.loc.gov/image-services/iiif/service:mss:mss11049:mss11049-002:00697/full/pct:12.5/0/default.jpg", "entry_id": 2}