{"dateText": "Friday 29.", "dateFormated": "1878-03-29", "cityOrState": "Seneca", "geographicalLocations": ["Ottawa"], "people": ["D. H. Underhill", "Cousin Ira House"], "fullText": "Seneca - Ill\nD. H. Underhill\nDark & Rainy night -\nLetter from Cousin\nIra House - of Ottawa\ninviting me to visit them -", "summaryText": "Susan B. Anthony was in Seneca, Illinois and received a letter from Cousin Ira House of Ottawa inviting her to visit them.", "digital_id": "mss11049.mss11049-002_00633_00763", "file_id": 37, "page": "https://tile.loc.gov/image-services/iiif/service:mss:mss11049:mss11049-002:00669/full/pct:12.5/0/default.jpg", "entry_id": 2}