{"dateText": "Friday, May 25, 1883", "dateFormated": "1883-05-25", "cityOrState": "Paris", "geographicalLocations": [], "people": ["Theodore", "Grace Greenwood", "Mr & Mrs Chain", "Miss Walton"], "fullText": "In Paris - In P.M. Theodore went with me to call on Grace Greenwood - also called on Mr & Mrs Chain & Miss Walton - but found them out - 11", "summaryText": "Susan B. Anthony visits Grace Greenwood, Mr. & Mrs. Chain, and Miss Walton in Paris with Theodore but finds them out.", "digital_id": "mss11049.mss11049-002_00764_01001", "file_id": 93, "page": "https://tile.loc.gov/image-services/iiif/service:mss:mss11049:mss11049-002:00856/full/pct:25/0/default.jpg", "entry_id": 2}