{"dateText": "Wea. WED. OCT. 26, 1898 Ther.", "dateFormated": "1898-10-26", "cityOrState": "Woman's National Convent\nOmaha - Neb -\nAt Paxton Hotel -", "geographicalLocations": ["Omaha", "Paxton Hotel"], "people": [], "fullText": "Wea. WED. OCT. 26, 1898 Ther.\nWoman's National Convent\nOmaha - Neb -\nAt Paxton Hotel -", "summaryText": "Susan B. Anthony wrote about attending the Woman's National Convention in Omaha on October 26, 1898, which was held at the Paxton Hotel.", "digital_id": "mss11049.mss11049-004_00231_00459", "file_id": 173, "page": "https://tile.loc.gov/image-services/iiif/service:mss:mss11049:mss11049-004:00403/full/pct:25/0/default.jpg", "entry_id": 2}