{"dateText": "NOVEMBER\n20 Sunday", "dateFormated": "1870-11-20", "cityOrState": "Belmont", "geographicalLocations": [""], "people": [""], "fullText": "Had delightful\nday in my room\nand visiting", "summaryText": "Susan B. Anthony had a delightful day in her room and visiting on November 20th in Belmont.", "digital_id": "mss11049.mss11049-001_00519_00682", "file_id": 128, "page": "https://tile.loc.gov/image-services/iiif/service:mss:mss11049:mss11049-001:00646/full/pct:12.5/0/default.jpg", "entry_id": 1}