{"dateText": "Wea Thur. May 5, 1898", "dateFormated": "1898-05-05", "cityOrState": "At Home", "geographicalLocations": ["Central Station", "Elmira"], "people": ["Miss Shaw"], "fullText": "At Home\nWent to Central Station\nwith Miss Shaw for the\n10.10 train for Elmira -\nwhere Conference is in\nprocess - began to rain", "summaryText": "Susan B. Anthony goes to the Central Station with Miss Shaw to catch a train to Elmira where a conference is in process.", "digital_id": "mss11049.mss11049-004_00231_00459", "file_id": 84, "page": "https://tile.loc.gov/image-services/iiif/service:mss:mss11049:mss11049-004:00314/full/pct:25/0/default.jpg", "entry_id": 2}